[{"DateOfRegistration":"2020-06-25T00:00:00+02:00","IsGuest":true,"Jmbg":"2602990102065","Name":"Ana Marija","Surname":"Rodic","Gender":1,"DateOfBirth":"1990-02-26T00:00:00","Phone":"063457852","Email":"mara990@hotmail.com","City":{"Name":"Novi Sad","ZipCode":21000},"HomeAddress":"Pasiceva 45","Username":"marija990","Password":"marija990"},{"DateOfRegistration":"2020-06-25T00:00:00+02:00","IsGuest":true,"Jmbg":"1805202564102","Name":"Dara","Surname":"Maric","Gender":1,"DateOfBirth":"2002-05-18T00:00:00","Phone":"061521478","Email":"dara202@hotmail.com","City":{"Name":"Novi Sad","ZipCode":21000},"HomeAddress":"Cara Lazara 52","Username":"daradara","Password":"daradara"},{"DateOfRegistration":"2020-06-23T00:00:00+02:00","IsGuest":true,"Jmbg":"0510995105452","Name":"Danilo","Surname":"Dakic","Gender":0,"DateOfBirth":"1995-10-05T00:00:00","Phone":"0654520145","Email":"danilod@hotmail.com","City":{"Name":"Zajecar","ZipCode":74050},"HomeAddress":"Njegoseva 21","Username":"danilo995","Password":"danilo995"},{"DateOfRegistration":"2020-06-25T00:00:00+02:00","IsGuest":false,"Jmbg":"5247895214520","Name":"Una","Surname":"Hristic","Gender":1,"DateOfBirth":"2020-06-05T00:00:00","Phone":"","Email":"","City":{"Name":"Novi Sad","ZipCode":21000},"HomeAddress":"Njegoseva","Username":"una12345","Password":"una12345"}]